MANIFEST.in
setup.py
bin/pandoc-gpp
include/html.gpp
include/latex.gpp
include/macros.gpp
pandoc_gpp.egg-info/PKG-INFO
pandoc_gpp.egg-info/SOURCES.txt
pandoc_gpp.egg-info/dependency_links.txt
pandoc_gpp.egg-info/requires.txt
pandoc_gpp.egg-info/top_level.txt
share/bin/evaluateExpression.py
share/bin/generate_graph.py
share/bin/generate_tabular.py
share/bin/includeFile.py